{
  "timestamp": "2022-06-27T17:00:00.000000Z",
  "bundleVersion": "1",
  "scenes": [
    {
      "_id": "CJVR-019",
      "scene_id": "cjvr00019",
      "scene_type": "VR",
      "title": "JK seduction leads to creampie VR at a love hotel after school. 3sex 16 ejaculation 190 min.",
      "studio": "Chijo Heaven",
      "site": "CJVR",
      "covers": [
        "https://pics.r18.com/digital/video/cjvr00019/cjvr00019pl.jpg"
      ],
      "gallery": [
        "https://pics.r18.com/digital/video/cjvr00019/cjvr00019jp-1.jpg","https://pics.r18.com/digital/video/cjvr00019/cjvr00019jp-2.jpg","https://pics.r18.com/digital/video/cjvr00019/cjvr00019jp-3.jpg","https://pics.r18.com/digital/video/cjvr00019/cjvr00019jp-4.jpg","https://pics.r18.com/digital/video/cjvr00019/cjvr00019jp-5.jpg","https://pics.r18.com/digital/video/cjvr00019/cjvr00019jp-6.jpg","https://pics.r18.com/digital/video/cjvr00019/cjvr00019jp-7.jpg","https://pics.r18.com/digital/video/cjvr00019/cjvr00019jp-8.jpg","https://pics.r18.com/digital/video/cjvr00019/cjvr00019jp-9.jpg","https://pics.r18.com/digital/video/cjvr00019/cjvr00019jp-10.jpg","https://pics.r18.com/digital/video/cjvr00019/cjvr00019jp-11.jpg","https://pics.r18.com/digital/video/cjvr00019/cjvr00019jp-12.jpg"
      ],
      "tags": [
        "Creampie","Schoolgirl","Uniform","Cowgirl","Slut","Beautiful Girl","Quack Quack","JAVR"
      ],
      "cast": [
        "Ichika Matsumoto"
      ],
      "synopsis": "[Seductive Immoral Pleasure VR] 3 SEX in large volume! 16 ejaculations! 16 ejaculations! Ichika and you, a teacher and a student, have an illicit relationship at a love hotel after school! Sensei...do you really like Ichika...? A cute student whispers in your ear and talks to you in a lewd way...you can't resist! She's riding him closely, getting her big ass pounded back, licking his nipples, and cumming a lot! I'm not a child anymore, okay? I know I'm not supposed to... but I can't stop getting an immoral boner! The ceiling and ground special effects give you a realistic feeling of being in the room! The brightness is also carefully selected! Please enjoy it!",
      "released": "2022-06-21",
      "homepage_url": "https://www.dmm.co.jp/digital/videoa/-/detail/=/cid=cjvr00019/",
      "duration": 188
    }
  ]
}
